{
  "version": "1.0.0",
  "restore": {
    "projectUniqueName": "/Users/ozu/RiderProjects/DartRefSandbox/DartRefSandbox/DartRefSandbox.csproj",
    "projectName": "DartRefSandbox",
    "projectPath": "/Users/ozu/RiderProjects/DartRefSandbox/DartRefSandbox/DartRefSandbox.csproj",
    "outputPath": "/Users/ozu/RiderProjects/DartRefSandbox/DartRefSandbox/obj/",
    "projectStyle": "PackageReference",
    "fallbackFolders": [
      "/usr/local/share/dotnet/sdk/NuGetFallbackFolder"
    ],
    "originalTargetFrameworks": [
      "netcoreapp2.2"
    ],
    "sources": {
      "https://api.nuget.org/v3/index.json": {}
    },
    "frameworks": {
      "netcoreapp2.2": {
        "projectReferences": {}
      }
    },
    "warningProperties": {
      "warnAsError": [
        "NU1605"
      ]
    }
  },
  "frameworks": {
    "netcoreapp2.2": {
      "dependencies": {
        "Microsoft.AspNetCore.Server.Kestrel": {
          "target": "Package",
          "version": "[2.2.0, )"
        },
        "Microsoft.NETCore.App": {
          "suppressParent": "All",
          "target": "Package",
          "version": "[2.2.0, )",
          "autoReferenced": true
        },
        "ServiceStack": {
          "target": "Package",
          "version": "[5.5.0, )"
        }
      },
      "imports": [
        "net461"
      ],
      "assetTargetFallback": true,
      "warn": true
    }
  }
}